kestrelcli
