Metadata-Version: 1.1
Name: kestrel-cli
Version: 0.0.7
Summary: kestrel command-line interface
Home-page: http://github.com/hogelog/kestrel-cli
Author: hogelog
Author-email: hogelog@hogel.org
License: MIT
Keywords: kestrel cli commandline
Platform: UNKNOWN
Classifier: Development Status :: 3 - Alpha
Classifier: Environment :: Console
Classifier: Topic :: Utilities
